{
  "id": "meatShop",
  "name": "鑲夐摵",
  "job": {
    "id": "meat_shop_owner",
    "name": "灞犲か",
    "heldItem": "minecraft:cooked_beef"
  },
  "containers": {
    "input": { "type": "structure_pos", "positions": [
[4, 1, 3], [5, 1, 3]
] },
    "output": { "type": "structure_pos", "positions": [
[4, 1, 3], [5, 1, 3]
] }
  },
  "offers": [
    {
      "id": "shop_sells_cooked_beef",
      "visibleTo": "mixed",
      "cost": [{ "money": 0.50 }],
      "result": [{ "item": "minecraft:cooked_beef", "count": 1 }],
      "stock": {
        "item": "minecraft:cooked_beef",
        "max": 64,
        "materials": [
          { "item": "minecraft:beef", "count": 1 }
        ]
      }
    },
    {
      "id": "shop_sells_cooked_porkchop",
      "visibleTo": "mixed",
      "cost": [{ "money": 0.50 }],
      "result": [{ "item": "minecraft:cooked_porkchop", "count": 1 }],
      "stock": {
        "item": "minecraft:cooked_porkchop",
        "max": 64,
        "materials": [
          { "item": "minecraft:porkchop", "count": 1 }
        ]
      }
    },
    {
      "id": "shop_buys_beef",
      "visibleTo": "player",
      "cost": [{ "item": "minecraft:beef", "count": 8 }],
      "result": [{ "money": 3.20 }],
      "stock": {
        "item": "minecraft:beef",
        "max": 128
      }
    },
    {
      "id": "shop_buys_porkchop",
      "visibleTo": "player",
      "cost": [{ "item": "minecraft:porkchop", "count": 8 }],
      "result": [{ "money": 3.20 }],
      "stock": {
        "item": "minecraft:porkchop",
        "max": 128
      }
    },
    {
      "id": "exchange_beef_for_cooked_beef",
      "visibleTo": "player",
      "cost": [{ "item": "minecraft:beef", "count": 1 }],
      "result": [{ "item": "minecraft:cooked_beef", "count": 1 }],
      "stock": {
        "item": "minecraft:cooked_beef",
        "max": 64
      }
    },
    {
      "id": "exchange_porkchop_for_cooked_porkchop",
      "visibleTo": "player",
      "cost": [{ "item": "minecraft:porkchop", "count": 1 }],
      "result": [{ "item": "minecraft:cooked_porkchop", "count": 1 }],
      "stock": {
        "item": "minecraft:cooked_porkchop",
        "max": 64
      }
    }
  ]
}
